guidelight/__init__.py
guidelight/client.py
guidelight/credentials.py
guidelight/exceptions.py
guidelight/url.py
guidelight/version.py
guidelight-0.2.2.dist-info/licenses/LICENSE
guidelight-0.2.2.dist-info/METADATA
guidelight-0.2.2.dist-info/WHEEL
guidelight-0.2.2.dist-info/top_level.txt
guidelight-0.2.2.dist-info/zip-safe
guidelight-0.2.2.dist-info/RECORD
